mfexport/__init__.py
mfexport/_version.py
mfexport/array_export.py
mfexport/budget_output.py
mfexport/grid.py
mfexport/inputs.py
mfexport/list_export.py
mfexport/listfile.py
mfexport/pdf_export.py
mfexport/results.py
mfexport/shapefile_export.py
mfexport/units.py
mfexport/utils.py
mfexport/zbud.py
mfexport/tests/__init__.py
mfexport/tests/conftest.py
mfexport/tests/test_array_export.py
mfexport/tests/test_grid.py
mfexport/tests/test_list_export.py
mfexport/tests/test_listfile.py
mfexport/tests/test_model_export.py
mfexport/tests/test_notebooks.py
mfexport/tests/test_results_export.py
mfexport/tests/test_rotation.py
mfexport/tests/test_units.py
mfexport/tests/test_utils.py
mfexport/tests/test_zbud.py
modflow_export-0.3.0.dist-info/LICENSE.md
modflow_export-0.3.0.dist-info/METADATA
modflow_export-0.3.0.dist-info/WHEEL
modflow_export-0.3.0.dist-info/entry_points.txt
modflow_export-0.3.0.dist-info/top_level.txt
modflow_export-0.3.0.dist-info/RECORD
