Metadata-Version: 2.1
Name: modflow-export
Version: 0.3.0
Summary: Fast & easy summarizing of MODFLOW data and export to GIS file formats
Author-email: Andrew Leaf <aleaf@usgs.gov>, Mike Fienen <mnfienen@usgs.gov>
License: License
Project-URL: documentation, https://aleaf.github.io/modflow-export/latest/
Project-URL: repository, https://github.com/aleaf/modflow-export
Keywords: MODFLOW,groundwater,hydrogeology
Classifier: Development Status :: 3 - Alpha
Classifier: Intended Audience :: Science/Research
Classifier: Programming Language :: Python :: 3 :: Only
Classifier: Topic :: Scientific/Engineering :: Hydrology
Requires-Python: >=3.11
License-File: LICENSE.md
Requires-Dist: gis-utils
Requires-Dist: fiona
Requires-Dist: flopy
Requires-Dist: matplotlib
Requires-Dist: numpy
Requires-Dist: pandas
Requires-Dist: pyproj
Requires-Dist: pyyaml
Requires-Dist: rasterio
Requires-Dist: shapely
Requires-Dist: xarray
Provides-Extra: docs
Requires-Dist: modflow-export[optional] ; extra == 'docs'
Requires-Dist: ipython[kernel] ; extra == 'docs'
Requires-Dist: sphinx ; extra == 'docs'
Requires-Dist: numpydoc ; extra == 'docs'
Requires-Dist: nbsphinx ; extra == 'docs'
Requires-Dist: sphinx-copybutton ; extra == 'docs'
Requires-Dist: sphinx-rtd-theme ; extra == 'docs'
Provides-Extra: optional
Provides-Extra: test
Requires-Dist: codecov ; extra == 'test'
Requires-Dist: coverage ; extra == 'test'
Requires-Dist: pytest ; extra == 'test'
